LICENSE
README.md
pyproject.toml
setup.py
torrentSearch/__init__.py
torrentSearch/__main__.py
torrentSearch/__version__.py
torrentSearch/default_config.ini
torrentSearch/http_utils.py
torrentSearch/jackett.py
torrentSearch/piratebay.py
torrentSearch/search.py
torrentSearch/torrent.py
torrentSearch/utils.py
torrentSearch.egg-info/PKG-INFO
torrentSearch.egg-info/SOURCES.txt
torrentSearch.egg-info/dependency_links.txt
torrentSearch.egg-info/entry_points.txt
torrentSearch.egg-info/requires.txt
torrentSearch.egg-info/top_level.txt
torrentSearch/tests/__init__.py
torrentSearch/tests/test_sample.py