Metadata-Version: 2.1
Name: torrentSearch
Version: 0.3.2.post4
Summary: Search For Torrents
Home-page: https://github.com/KevinMidboe/torrent_search
Author: KevinMidboe
License: UNKNOWN
Platform: UNKNOWN
Classifier: Programming Language :: Python
Classifier: Operating System :: OS Independent
Classifier: Programming Language :: Python :: 3.6
License-File: LICENSE
